karray/__init__.py
karray/constants.py
karray/py.typed
karray/source_code.py
karray-2024.3.7.dist-info/LICENSE
karray-2024.3.7.dist-info/METADATA
karray-2024.3.7.dist-info/WHEEL
karray-2024.3.7.dist-info/top_level.txt
karray-2024.3.7.dist-info/RECORD
