Metadata-Version: 2.1
Name: karray
Version: 2024.3.7
Summary: Lightweight labelled multidimensional arrays with NumPy arrays under the hood.
Author-email: Carlos Gaete-Morales <cdgaete@gmail.com>
License: MIT License
Project-URL: Documentation, https://diw-evu.gitlab.io/karray
Project-URL: Source-code, https://gitlab.com/diw-evu/karray
Project-URL: Issue-tracker, https://gitlab.com/diw-evu/karray/issues
Keywords: ndarray,labeled,multidimensional,element-wise,dense,sparse,arrays
Classifier: Intended Audience :: Science/Research
Classifier: License :: OSI Approved :: MIT License
Classifier: Operating System :: MacOS :: MacOS X
Classifier: Operating System :: Microsoft :: Windows
Classifier: Operating System :: POSIX
Classifier: Programming Language :: Python
Classifier: Programming Language :: Python :: 3
Classifier: Programming Language :: Python :: 3.7
Classifier: Programming Language :: Python :: 3.8
Classifier: Programming Language :: Python :: 3.9
Classifier: Programming Language :: Python :: 3.10
Classifier: Programming Language :: Python :: 3.11
Classifier: Topic :: Scientific/Engineering
Requires-Python: >=3.7
License-File: LICENSE
Requires-Dist: numpy >=1.22.4
Provides-Extra: all
Requires-Dist: karray[io,sparse] ; extra == 'all'
Provides-Extra: io
Requires-Dist: pyarrow ; extra == 'io'
Requires-Dist: pandas ; extra == 'io'
Requires-Dist: polars ; extra == 'io'
Provides-Extra: pandas
Requires-Dist: pyarrow ; extra == 'pandas'
Requires-Dist: pandas ; extra == 'pandas'
Provides-Extra: polars
Requires-Dist: pyarrow ; extra == 'polars'
Requires-Dist: polars ; extra == 'polars'
Provides-Extra: sparse
Requires-Dist: sparse ; extra == 'sparse'
